hdf5widget/__init__.py
hdf5widget/hdf5object.py
hdf5widget/hdf5widget.py
hdf5widget-0.1.0.dist-info/DESCRIPTION.rst
hdf5widget-0.1.0.dist-info/METADATA
hdf5widget-0.1.0.dist-info/RECORD
hdf5widget-0.1.0.dist-info/WHEEL
hdf5widget-0.1.0.dist-info/metadata.json
hdf5widget-0.1.0.dist-info/top_level.txt
