Metadata-Version: 2.0
Name: hdf5widget
Version: 0.1.0
Summary: This is hdf5widget, a widget for viewing the contents of a HDF5-file in Jupyter Notebooks using ipywidgets.
Home-page: https://github.com/m-rossi/hdf5widget
Author: Marco Rossi
Author-email: developer@marco-rossi.com
License: MIT
Keywords: jupyter,hdf5,notebook
Platform: UNKNOWN
Classifier: Operating System :: OS Independent
Classifier: Development Status :: 3 - Alpha
Classifier: Framework :: Jupyter
Classifier: License :: OSI Approved :: MIT License
Classifier: Programming Language :: Python :: 3.6
Requires-Python: >=3.6
Requires-Dist: h5py
Requires-Dist: ipywidgets (>=7.0)
